odoo/addons/hr_timesheet_time_type/README.rst
odoo/addons/hr_timesheet_time_type/__init__.py
odoo/addons/hr_timesheet_time_type/__manifest__.py
odoo/addons/hr_timesheet_time_type/i18n/es.po
odoo/addons/hr_timesheet_time_type/i18n/fr.po
odoo/addons/hr_timesheet_time_type/i18n/hr_timesheet_time_type.pot
odoo/addons/hr_timesheet_time_type/i18n/it.po
odoo/addons/hr_timesheet_time_type/i18n/pt_BR.po
odoo/addons/hr_timesheet_time_type/models/__init__.py
odoo/addons/hr_timesheet_time_type/models/account_analytic_line.py
odoo/addons/hr_timesheet_time_type/models/project_time_type.py
odoo/addons/hr_timesheet_time_type/readme/CONTRIBUTORS.md
odoo/addons/hr_timesheet_time_type/readme/CREDITS.md
odoo/addons/hr_timesheet_time_type/readme/DESCRIPTION.md
odoo/addons/hr_timesheet_time_type/security/ir.model.access.csv
odoo/addons/hr_timesheet_time_type/static/description/icon.png
odoo/addons/hr_timesheet_time_type/static/description/index.html
odoo/addons/hr_timesheet_time_type/views/account_analytic_line_view.xml
odoo/addons/hr_timesheet_time_type/views/project_time_type_view.xml
odoo_addon_hr_timesheet_time_type-18.0.1.0.0.2.dist-info/METADATA
odoo_addon_hr_timesheet_time_type-18.0.1.0.0.2.dist-info/WHEEL
odoo_addon_hr_timesheet_time_type-18.0.1.0.0.2.dist-info/top_level.txt
odoo_addon_hr_timesheet_time_type-18.0.1.0.0.2.dist-info/RECORD
